pypasswork/__init__.py
pypasswork/__version__.py
pypasswork/exceptions.py
pypasswork/passwork.py
pypasswork/request.py
pypasswork/response.py
pypasswork/operations/__init__.py
pypasswork/operations/folders.py
pypasswork/operations/passwords.py
pypasswork/operations/vaults.py
pypasswork-0.0.4.dist-info/LICENSE
pypasswork-0.0.4.dist-info/METADATA
pypasswork-0.0.4.dist-info/WHEEL
pypasswork-0.0.4.dist-info/top_level.txt
pypasswork-0.0.4.dist-info/RECORD
