Metadata-Version: 2.1
Name: pypasswork
Version: 0.0.4
Summary: Passwork API library
Author-email: Khatsayuk Alexander <asand3r@ya.ru>
License: MIT
Classifier: Programming Language :: Python :: 3
Classifier: License :: OSI Approved :: MIT License
Classifier: Operating System :: OS Independent
Requires-Python: >=3.10
License-File: LICENSE
Requires-Dist: requests >=2.30.0
Provides-Extra: dev
Requires-Dist: pre-commit ; extra == 'dev'
